INSTALL
LICENSE
MANIFEST.in
README.md
setup.cfg
setup.py
redis55/__init__.py
redis55/async_timeout.py
redis55/backoff.py
redis55/client.py
redis55/cluster.py
redis55/compat.py
redis55/connection.py
redis55/crc.py
redis55/credentials.py
redis55/exceptions.py
redis55/lock.py
redis55/ocsp.py
redis55/retry.py
redis55/sentinel.py
redis55/typing.py
redis55/utils.py
redis55.egg-info/PKG-INFO
redis55.egg-info/SOURCES.txt
redis55.egg-info/dependency_links.txt
redis55.egg-info/requires.txt
redis55.egg-info/top_level.txt
redis55/_parsers/__init__.py
redis55/_parsers/base.py
redis55/_parsers/commands.py
redis55/_parsers/encoders.py
redis55/_parsers/helpers.py
redis55/_parsers/hiredis.py
redis55/_parsers/resp2.py
redis55/_parsers/resp3.py
redis55/_parsers/socket.py
redis55/asyncio/__init__.py
redis55/asyncio/client.py
redis55/asyncio/cluster.py
redis55/asyncio/connection.py
redis55/asyncio/lock.py
redis55/asyncio/retry.py
redis55/asyncio/sentinel.py
redis55/asyncio/utils.py
redis55/commands/__init__.py
redis55/commands/cluster.py
redis55/commands/core.py
redis55/commands/helpers.py
redis55/commands/redismodules.py
redis55/commands/sentinel.py
redis55/commands/bf/__init__.py
redis55/commands/bf/commands.py
redis55/commands/bf/info.py
redis55/commands/graph/__init__.py
redis55/commands/graph/commands.py
redis55/commands/graph/edge.py
redis55/commands/graph/exceptions.py
redis55/commands/graph/execution_plan.py
redis55/commands/graph/node.py
redis55/commands/graph/path.py
redis55/commands/graph/query_result.py
redis55/commands/json/__init__.py
redis55/commands/json/_util.py
redis55/commands/json/commands.py
redis55/commands/json/decoders.py
redis55/commands/json/path.py
redis55/commands/search/__init__.py
redis55/commands/search/_util.py
redis55/commands/search/aggregation.py
redis55/commands/search/commands.py
redis55/commands/search/document.py
redis55/commands/search/field.py
redis55/commands/search/indexDefinition.py
redis55/commands/search/query.py
redis55/commands/search/querystring.py
redis55/commands/search/reducers.py
redis55/commands/search/result.py
redis55/commands/search/suggestion.py
