Metadata-Version: 2.1
Name: redis55
Version: 1.0.2
Summary: redis55 is forked from redis 5.0.0, so you can use redis55 and any version redis in one python env
Home-page: 
Author: Redis Inc.
Author-email: 
License: MIT
Keywords: Redis,key-value store,database
Classifier: Development Status :: 5 - Production/Stable
Classifier: Environment :: Console
Classifier: Intended Audience :: Developers
Classifier: License :: OSI Approved :: MIT License
Classifier: Operating System :: OS Independent
Classifier: Programming Language :: Python
Classifier: Programming Language :: Python :: 3
Classifier: Programming Language :: Python :: 3 :: Only
Classifier: Programming Language :: Python :: 3.7
Classifier: Programming Language :: Python :: 3.8
Classifier: Programming Language :: Python :: 3.9
Classifier: Programming Language :: Python :: 3.10
Classifier: Programming Language :: Python :: 3.11
Classifier: Programming Language :: Python :: Implementation :: CPython
Classifier: Programming Language :: Python :: Implementation :: PyPy
Requires-Python: >=3.7
Provides-Extra: hiredis
Provides-Extra: ocsp
License-File: LICENSE
